chatterbot_voice/__init__.py
chatterbot_voice/voice.py
chatterbot_voice-0.1.3.dist-info/DESCRIPTION.rst
chatterbot_voice-0.1.3.dist-info/METADATA
chatterbot_voice-0.1.3.dist-info/RECORD
chatterbot_voice-0.1.3.dist-info/WHEEL
chatterbot_voice-0.1.3.dist-info/metadata.json
chatterbot_voice-0.1.3.dist-info/top_level.txt
chatterbot_voice-0.1.3.dist-info/zip-safe
